anystruct/ANYstructure_documentation.pdf
anystruct/SN_curve_parameters.py
anystruct/__init__.py
anystruct/__main__.py
anystruct/api.py
anystruct/buckling_calc_external.py
anystruct/bulb_anglebar_tbar_flatbar.csv
anystruct/calc_loads.py
anystruct/calc_structure.py
anystruct/compartment_window.py
anystruct/example_data.py
anystruct/example_data_puls.py
anystruct/excel_inteface.py
anystruct/fatigue_window.py
anystruct/grid_window.py
anystruct/gui.py
anystruct/helper.py
anystruct/load_factor_window.py
anystruct/load_window.py
anystruct/main_application.py
anystruct/make_grid_numpy.py
anystruct/make_queue.py
anystruct/make_stack.py
anystruct/opt_problem.py
anystruct/optimize.py
anystruct/optimize_cylinder.py
anystruct/optimize_geometry.py
anystruct/optimize_multiple_window.py
anystruct/optimize_window.py
anystruct/pl_stf_window.py
anystruct/report_generator.py
anystruct/sections.csv
anystruct/sesam_interface.py
anystruct/ship_section_example.txt
anystruct/stresses_window.py
anystruct/testCalc.py
anystruct/images/ANYstructure_logo.jpg
anystruct/images/Buckling_Strength_of_Shells.png
anystruct/images/Panel_geometry_definitions.png
anystruct/images/current_comps_NONE.png
anystruct/images/cylinder_opt.png
anystruct/images/fls_button.gif
anystruct/images/img_T_L_FB.gif
anystruct/images/img_axial_stresses.gif
anystruct/images/img_ext_pressure_button.gif
anystruct/images/img_ext_pressure_button_def.gif
anystruct/images/img_fixation_parameters.gif
anystruct/images/img_generate_report.gif
anystruct/images/img_int_pressure_button.gif
anystruct/images/img_int_pressure_button_search.gif
anystruct/images/img_multi_opt.gif
anystruct/images/img_optimize.gif
anystruct/images/img_plate_and_stiffener.gif
anystruct/images/img_stf_button.gif
anystruct/images/img_stiffener.gif
anystruct/images/img_stress_button.gif
anystruct/images/img_title.gif
anystruct/images/img_transverse_stress.gif
anystruct/ml_files/CL_CSR-Tank_req_cl_predictor.pickle
anystructure-5.3.3.dist-info/licenses/LICENSE
anystructure-5.3.3.dist-info/METADATA
anystructure-5.3.3.dist-info/WHEEL
anystructure-5.3.3.dist-info/entry_points.txt
anystructure-5.3.3.dist-info/top_level.txt
anystructure-5.3.3.dist-info/RECORD
