Metadata-Version: 2.4
Name: ANYstructure
Version: 5.3.3
Summary: A plate field optimization tool for offshore structures calculated according to DNV standards
Home-page: https://github.com/audunarn/ANYstructure
Author: Audun Arnesen Nyhus
Author-email: audunarn@gmail.com
License: MIT
Keywords: dnv-gl-os-c101 dnv-rp-c202 dnv-rp-c201 naval_architecture structural_engineering steel buckling fatigue local_scantlings optimization weight
Classifier: Development Status :: 5 - Production/Stable
Classifier: Environment :: X11 Applications
Classifier: License :: OSI Approved :: MIT License
Classifier: Programming Language :: Python :: 3.13
Classifier: Topic :: Scientific/Engineering
License-File: LICENSE
Requires-Dist: scipy
Requires-Dist: numpy
Requires-Dist: matplotlib
Requires-Dist: reportlab
Requires-Dist: xlwings
Requires-Dist: scikit-learn
Dynamic: author
Dynamic: author-email
Dynamic: classifier
Dynamic: description
Dynamic: home-page
Dynamic: keywords
Dynamic: license
Dynamic: license-file
Dynamic: requires-dist
Dynamic: summary
